setup.py
python_testcase_generator/__init__.py
python_testcase_generator/builtin.py
python_testcase_generator/evaluation.py
python_testcase_generator/expression.py
python_testcase_generator/generator.py
python_testcase_generator/main.py
python_testcase_generator/setting.py
python_testcase_generator.egg-info/PKG-INFO
python_testcase_generator.egg-info/SOURCES.txt
python_testcase_generator.egg-info/dependency_links.txt
python_testcase_generator.egg-info/entry_points.txt
python_testcase_generator.egg-info/top_level.txt
test/test_bracket.py
test/test_builtin.py
test/test_quotes.py
test/test_syntax.py
test/test_type.py