Metadata-Version: 1.1
Name: python-testcase-generator
Version: 1.0
Summary: A testcase generator that can generate a test case from Python expression
Home-page: https://github.com/tjkendev/python-testcase-generator
Author: yaketake08
Author-email: jake-basu@hotmail.co.jp
License: UNKNOWN
Platform: UNKNOWN
Classifier: Environment :: Console
Classifier: Intended Audience :: Developers
Classifier: License :: OSI Approved :: MIT License
Classifier: Operating System :: MacOS
Classifier: Operating System :: POSIX
Classifier: Programming Language :: Python
